dolomite_mae/__init__.py
dolomite_mae/read_multi_assay_experiment.py
dolomite_mae/save_multi_assay_experiment.py
dolomite_mae-0.2.0.dist-info/LICENSE.txt
dolomite_mae-0.2.0.dist-info/METADATA
dolomite_mae-0.2.0.dist-info/WHEEL
dolomite_mae-0.2.0.dist-info/top_level.txt
dolomite_mae-0.2.0.dist-info/RECORD
