Metadata-Version: 2.1
Name: dolomite-mae
Version: 0.2.0
Summary: Save and load multi-assay experiments in the dolomite framework!
Home-page: https://github.com/ArtifactDB/dolomite-mae
Author: Jayaram Kancherla
Author-email: jayaram.kancherla@gmail.com
License: MIT
Project-URL: Documentation, https://github.com/ArtifactDB/dolomite-mae
Platform: any
Classifier: Development Status :: 4 - Beta
Classifier: Programming Language :: Python
Requires-Python: >=3.9
License-File: LICENSE.txt
Requires-Dist: importlib-metadata; python_version < "3.8"
Requires-Dist: dolomite-base>=0.4.2
Requires-Dist: dolomite_sce>=0.3.0
Requires-Dist: dolomite_se>=0.3.0
Requires-Dist: multiassayexperiment>=0.4.2
Requires-Dist: biocutils
Requires-Dist: pandas
Requires-Dist: numpy
Provides-Extra: testing
Requires-Dist: setuptools; extra == "testing"
Requires-Dist: pytest; extra == "testing"
Requires-Dist: pytest-cov; extra == "testing"
